weblate/__init__.py
weblate/logger.py
weblate/middleware.py
weblate/models.py
weblate/py.typed
weblate/runner.py
weblate/settings_docker.py
weblate/settings_example.py
weblate/settings_test.py
weblate/sitemaps.py
weblate/urls.py
weblate/wsgi.py
weblate/accounts/__init__.py
weblate/accounts/admin.py
weblate/accounts/apps.py
weblate/accounts/auth.py
weblate/accounts/avatar.py
weblate/accounts/captcha.py
weblate/accounts/data.py
weblate/accounts/forms.py
weblate/accounts/middleware.py
weblate/accounts/models.py
weblate/accounts/notifications.py
weblate/accounts/password_validation.py
weblate/accounts/pipeline.py
weblate/accounts/strategy.py
weblate/accounts/tasks.py
weblate/accounts/types.py
weblate/accounts/urls.py
weblate/accounts/utils.py
weblate/accounts/views.py
weblate/accounts/management/__init__.py
weblate/accounts/management/commands/__init__.py
weblate/accounts/management/commands/dumpuserdata.py
weblate/accounts/management/commands/importuserdata.py
weblate/accounts/migrations/0001_squashed_weblate_5.py
weblate/accounts/migrations/0002_new_string_notification.py
weblate/accounts/migrations/0003_alter_auditlog_activity.py
weblate/accounts/migrations/0004_alter_profile_twitter.py
weblate/accounts/migrations/0005_verifiedemail_accounts_verifiedemail_email.py
weblate/accounts/migrations/0006_alter_auditlog_activity.py
weblate/accounts/migrations/0007_alter_profile_codesite_alter_profile_fediverse_and_more.py
weblate/accounts/migrations/0008_alter_auditlog_activity.py
weblate/accounts/migrations/0009_alter_profile_dashboard_view.py
weblate/accounts/migrations/0010_alter_subscription_notification.py
weblate/accounts/migrations/0011_alter_subscription_notification.py
weblate/accounts/migrations/0012_alter_auditlog_activity_profile_last_2fa.py
weblate/accounts/migrations/0013_bot_notifications.py
weblate/accounts/migrations/0014_alter_subscription_unique_together_and_more.py
weblate/accounts/migrations/0015_alter_auditlog_activity.py
weblate-5.15.2.dist-info/licenses/LICENSE
weblate-5.15.2.dist-info/METADATA
weblate-5.15.2.dist-info/WHEEL
weblate-5.15.2.dist-info/entry_points.txt
weblate-5.15.2.dist-info/top_level.txt
weblate-5.15.2.dist-info/RECORD
